stix_shifter_modules/qradar_perf_test/__init__.py
stix_shifter_modules/qradar_perf_test/entry_point.py
stix_shifter_modules/qradar_perf_test/configuration/config.json
stix_shifter_modules/qradar_perf_test/configuration/dialects.json
stix_shifter_modules/qradar_perf_test/configuration/lang_en.json
stix_shifter_modules/qradar_perf_test/stix_translation/__init__.py
stix_shifter_modules/qradar_perf_test/stix_translation/aql_query_translator.py
stix_shifter_modules/qradar_perf_test/stix_translation/json_to_stix_translator.py
stix_shifter_modules/qradar_perf_test/stix_translation/qradar_utils.py
stix_shifter_modules/qradar_perf_test/stix_translation/query_constructor.py
stix_shifter_modules/qradar_perf_test/stix_translation/query_translator.py
stix_shifter_modules/qradar_perf_test/stix_translation/transformers.py
stix_shifter_modules/qradar_perf_test/stix_translation/json/aql_events_fields.json
stix_shifter_modules/qradar_perf_test/stix_translation/json/events_from_stix_map.json
stix_shifter_modules/qradar_perf_test/stix_translation/json/network_protocol_map.json
stix_shifter_modules/qradar_perf_test/stix_translation/json/operators.json
stix_shifter_modules/qradar_perf_test/stix_translation/json/to_stix_map.json
stix_shifter_modules/qradar_perf_test/stix_translation/json/stix_2_1/events_from_stix_map.json
stix_shifter_modules/qradar_perf_test/stix_translation/json/stix_2_1/to_stix_map.json
stix_shifter_modules/qradar_perf_test/stix_transmission/__init__.py
stix_shifter_modules/qradar_perf_test/stix_transmission/connector.py
stix_shifter_modules/qradar_perf_test/stix_transmission/error_mapper.py
stix_shifter_modules_qradar_perf_test-8.0.2.dist-info/licenses/AUTHORS.md
stix_shifter_modules_qradar_perf_test-8.0.2.dist-info/licenses/LICENSE.md
stix_shifter_modules_qradar_perf_test-8.0.2.dist-info/licenses/NOTICE
stix_shifter_modules_qradar_perf_test-8.0.2.dist-info/METADATA
stix_shifter_modules_qradar_perf_test-8.0.2.dist-info/WHEEL
stix_shifter_modules_qradar_perf_test-8.0.2.dist-info/top_level.txt
stix_shifter_modules_qradar_perf_test-8.0.2.dist-info/RECORD
